ai_finance_agent-0.1.2.dist-info/licenses/LICENSE
finance_agent/__init__.py
finance_agent/agent.py
finance_agent/config.py
finance_agent/exceptions.py
finance_agent/models.py
finance_agent/ocr_processor.py
finance_agent/utils.py
ai_finance_agent-0.1.2.dist-info/METADATA
ai_finance_agent-0.1.2.dist-info/WHEEL
ai_finance_agent-0.1.2.dist-info/top_level.txt
ai_finance_agent-0.1.2.dist-info/RECORD
