Metadata-Version: 2.4
Name: ai-finance-agent
Version: 0.1.2
Summary: An agentic AI library for processing financial receipts
Author-email: Yauheniya Varabyova <yauheniya.ail@gmail.com>
Maintainer-email: Yauheniya Varabyova <yauheniya.ail@gmail.com>
License: MIT
Project-URL: Homepage, https://github.com/yauheniya-ai/ai-finance-agent
Project-URL: Documentation, https://ai-finance-agent.readthedocs.io/
Project-URL: Repository, https://github.com/yauheniya-ai/ai-finance-agent
Project-URL: Bug Tracker, https://github.com/yauheniya-ai/ai-finance-agent/issues
Project-URL: Changelog, https://github.com/yauheniya-ai/ai-finance-agent/blob/main/CHANGELOG.md
Keywords: finance,receipts,ocr,ai,llm,agent,extraction
Classifier: Development Status :: 3 - Alpha
Classifier: Intended Audience :: Developers
Classifier: License :: OSI Approved :: MIT License
Classifier: Operating System :: OS Independent
Classifier: Programming Language :: Python :: 3
Classifier: Programming Language :: Python :: 3.8
Classifier: Programming Language :: Python :: 3.9
Classifier: Programming Language :: Python :: 3.10
Classifier: Programming Language :: Python :: 3.11
Classifier: Programming Language :: Python :: 3.12
Classifier: Topic :: Office/Business :: Financial
Classifier: Topic :: Scientific/Engineering :: Artificial Intelligence
Classifier: Topic :: Text Processing :: Indexing
Classifier: Topic :: Multimedia :: Graphics :: Capture :: Digital Camera
Requires-Python: >=3.8
License-File: LICENSE
Requires-Dist: requests>=2.28.0
Requires-Dist: PyMuPDF>=1.22.0
Requires-Dist: pytesseract>=0.3.10
Requires-Dist: Pillow>=9.0.0
Requires-Dist: opencv-python>=4.6.0
Requires-Dist: numpy>=1.21.0
Requires-Dist: python-dateutil>=2.8.0
Provides-Extra: dev
Requires-Dist: pytest>=7.0; extra == "dev"
Requires-Dist: pytest-cov>=4.0; extra == "dev"
Requires-Dist: black>=22.0; extra == "dev"
Requires-Dist: flake8>=5.0; extra == "dev"
Requires-Dist: mypy>=0.991; extra == "dev"
Requires-Dist: pre-commit>=2.20.0; extra == "dev"
Provides-Extra: docs
Requires-Dist: sphinx>=5.0; extra == "docs"
Requires-Dist: sphinx-rtd-theme>=1.0; extra == "docs"
Requires-Dist: myst-parser>=0.18; extra == "docs"
Provides-Extra: test
Requires-Dist: pytest>=7.0; extra == "test"
Requires-Dist: pytest-cov>=4.0; extra == "test"
Requires-Dist: pytest-mock>=3.8.0; extra == "test"
Requires-Dist: responses>=0.21.0; extra == "test"
Dynamic: license-file
